ng_bot/__init__.py
ng_bot/__main__.py
ng_bot/bot.py
ng_bot/discord.py
ng_bot/ngrok_wrapper.py
ng_bot-1.0.3.dist-info/LICENSE
ng_bot-1.0.3.dist-info/WHEEL
ng_bot-1.0.3.dist-info/METADATA
ng_bot-1.0.3.dist-info/RECORD
