Metadata-Version: 2.1
Name: ng-bot
Version: 1.0.3
Summary: Bot Integrations with various platforms to send latest ngork links
License: MIT
Author: Dhrumil Mistry
Author-email: 56185972+dmdhrumilmistry@users.noreply.github.com
Requires-Python: >=3.8,<4.0
Classifier: License :: OSI Approved :: MIT License
Classifier: Programming Language :: Python :: 3
Classifier: Programming Language :: Python :: 3.8
Classifier: Programming Language :: Python :: 3.9
Classifier: Programming Language :: Python :: 3.10
Classifier: Programming Language :: Python :: 3.11
Requires-Dist: prettytable (>=3.6.0,<4.0.0)
Requires-Dist: pyngrok (>=5.2.1,<6.0.0)
Requires-Dist: pytelegrambotapi (>=4.10.0,<5.0.0)
Requires-Dist: python-dotenv (>=0.21.1,<0.22.0)
Requires-Dist: requests (>=2.28.2,<3.0.0)
